Metadata-Version: 2.1
Name: oh-my-email
Version: 0.1.0
Summary: simple send email in python
Home-page: https://github.com/jiangyx3915/oh-my-email
Author: Jiang Yi Xin
Author-email: 15221613915@163.com
License: MPL-2.0
Platform: UNKNOWN
Classifier: Development Status :: 3 - Alpha
Classifier: Intended Audience :: Science/Research
Classifier: Programming Language :: Python :: 2.7
Classifier: Programming Language :: Python :: 3.6
